s_coda/__init__.py
s_coda/settings.py
s_coda/elements/__init__.py
s_coda/elements/bar.py
s_coda/elements/composition.py
s_coda/elements/message.py
s_coda/elements/track.py
s_coda/exception/__init__.py
s_coda/exception/exceptions.py
s_coda/sequence/__init__.py
s_coda/sequence/absolute_sequence.py
s_coda/sequence/abstract_sequence.py
s_coda/sequence/relative_sequence.py
s_coda/sequence/sequence.py
s_coda/util/__init__.py
s_coda/util/logging.py
s_coda/util/midi_wrapper.py
s_coda/util/music_theory.py
s_coda/util/util.py
s_coda-1.0.dist-info/LICENSE.md
s_coda-1.0.dist-info/METADATA
s_coda-1.0.dist-info/WHEEL
s_coda-1.0.dist-info/top_level.txt
s_coda-1.0.dist-info/RECORD
