Metadata-Version: 2.1
Name: s-coda
Version: 1.0
Summary: A library for handling and modifying MIDI files
Author: Felix Schön
License: MIT
License-File: LICENSE.md
Requires-Dist: mido (>=1.2.10)
Requires-Dist: numpy (>=1.22.2)
Requires-Dist: matplotlib (>=3.5.1)
Requires-Dist: pandas (>=1.4.1)
